datality/__init__.py
datality/avl.py
datality/bit_mask.py
datality/bst.py
datality/deque.py
datality/disjoint_set.py
datality/double_linked_list.py
datality/fenwick_tree.py
datality/linked_list.py
datality/min_heap.py
datality/radix_trie.py
datality/rb_tree.py
datality/segment_tree.py
datality/skip_list.py
datality/splay_tree.py
datality/treap.py
datality/trie.py
datality/van_emde_boas.py
datality-0.1.3.dist-info/LICENSE
datality-0.1.3.dist-info/WHEEL
datality-0.1.3.dist-info/METADATA
datality-0.1.3.dist-info/RECORD
