Metadata-Version: 2.1
Name: datality
Version: 0.1.3
Summary: this package contains implementations from the classic datas tructures in the CLRS
Author: Zetinator
Author-email: erick_zetina@hotmail.com
Requires-Python: >=3.8,<4.0
Classifier: Programming Language :: Python :: 3
Classifier: Programming Language :: Python :: 3.8
Classifier: Programming Language :: Python :: 3.9
